setup.py
f3authjwt/__init__.py
f3authjwt/application.py
f3authjwt/authentication_types.py
f3authjwt/helpers.py
f3authjwt/models.py
f3authjwt.egg-info/PKG-INFO
f3authjwt.egg-info/SOURCES.txt
f3authjwt.egg-info/dependency_links.txt
f3authjwt.egg-info/not-zip-safe
f3authjwt.egg-info/requires.txt
f3authjwt.egg-info/top_level.txt