Metadata-Version: 1.0
Name: f3authjwt
Version: 0.3.1
Summary: Module to secure endpoints using jwt token in ferris 3 framework
Home-page: https://github.com/handerson2014/f3authjwt
Author: Handerson Contreras
Author-email: handerson.contreras@gmail.com
License: MIT
Platform: UNKNOWN
